mannkendall/__init__.py
mannkendall/mk_hardcoded.py
mannkendall/mk_main.py
mannkendall/mk_stats.py
mannkendall/mk_tools.py
mannkendall/mk_version.py
mannkendall/mk_white.py
mannkendall-1.1.1.dist-info/AUTHORS
mannkendall-1.1.1.dist-info/LICENSE
mannkendall-1.1.1.dist-info/METADATA
mannkendall-1.1.1.dist-info/WHEEL
mannkendall-1.1.1.dist-info/top_level.txt
mannkendall-1.1.1.dist-info/RECORD
